wordhasher/__init__.py
wordhasher/__main__.py
wordhasher/adjectives.txt
wordhasher/nouns.txt
wordhasher/verbs.txt
wordhasher/wordhasher.py
wordhasher-0.2.0.dist-info/LICENSE
wordhasher-0.2.0.dist-info/METADATA
wordhasher-0.2.0.dist-info/WHEEL
wordhasher-0.2.0.dist-info/entry_points.txt
wordhasher-0.2.0.dist-info/top_level.txt
wordhasher-0.2.0.dist-info/RECORD
