Metadata-Version: 2.1
Name: wordhasher
Version: 0.2.0
Summary: Make comparing hashes more human friendly by using verb-adj-noun format.
Author-email: lfrati <lfrati.github@gmail.com>
License: MIT
Project-URL: Homepage, https://github.com/lfrati/wordhasher
Keywords: hashing
Classifier: License :: OSI Approved :: MIT License
Classifier: Programming Language :: Python :: 3
Requires-Python: >=3.9
License-File: LICENSE
Provides-Extra: dev
Requires-Dist: tqdm ; extra == 'dev'
Requires-Dist: bumpver ; extra == 'dev'
Requires-Dist: pip-tools ; extra == 'dev'
Requires-Dist: build ; extra == 'dev'
Requires-Dist: twine ; extra == 'dev'
Requires-Dist: pytest ; extra == 'dev'
